{"_id":"eval_sd_001","course_id":"course_software_design","course_offering_id":"offering_sd_2026s","teacher_ids":["teacher_001"],"token_hash":"sha256$evalsd001","scores":{"content":5,"teaching_method":5,"difficulty":3,"workload":4,"achievement":5,"overall":5},"difficulty_score":3,"workload_score":4,"feedback_text":"Practical and helpful for real project architecture.","status":"submitted","submitted_at":1779336000000,"created_at":1779336000000,"updated_at":1779336000000}
{"_id":"eval_da_001","course_id":"course_data_analysis","course_offering_id":"offering_da_2026s","teacher_ids":["teacher_001"],"token_hash":"sha256$evalda001","scores":{"content":5,"teaching_method":4,"difficulty":3,"workload":3,"achievement":4,"overall":4},"difficulty_score":3,"workload_score":3,"feedback_text":"Good for students interested in data analysis.","status":"submitted","submitted_at":1779422400000,"created_at":1779422400000,"updated_at":1779422400000}
